mkdocs_argparse/__init__.py
mkdocs_argparse-0.0.1.dist-info/LICENSE
mkdocs_argparse-0.0.1.dist-info/METADATA
mkdocs_argparse-0.0.1.dist-info/WHEEL
mkdocs_argparse-0.0.1.dist-info/entry_points.txt
mkdocs_argparse-0.0.1.dist-info/top_level.txt
mkdocs_argparse-0.0.1.dist-info/RECORD
